[
  {
    "photo1": "https://encrypted-tbn0.gstatic.com/images?q=tbn:ANd9GcSK6lm1ll8FOIx9yvcoP3hwmvbz0mgYIrRPwS72WUcHJg&s=10",
    "name1": "Macédoine du Nord",
    "photo2": "https://encrypted-tbn0.gstatic.com/images?q=tbn:ANd9GcT6I3aGCxXV3N_CvclKq5f8N7hePyZmJjIDdcsci4hP5g&s=10",
    "name2": "Irlande",
    "champ": "Basket-ball. Championna d'Europe FIBA",
    "heure": "16H00",
    "date": "02/07/2026",
    "pro": "Equipe gagne: V1"
  },
  {
    "photo1": "https://upload.wikimedia.org/wikipedia/commons/thumb/1/1f/Flag_of_Kosovo.svg/1280px-Flag_of_Kosovo.svg.png",
    "name1": "Kosovo",
    "photo2": "https://encrypted-tbn0.gstatic.com/images?q=tbn:ANd9GcRNeoP7BPrvYr4za5EjSSoBSTV_QAthiqAUOBEt4sVqvg&s",
    "name2": "Albanie",
    "champ": "Basket-ball. Championna d'Europe FIBA",
    "heure": "17H00",
    "date": "02/07/2026",
    "pro": "Equipe gagne: V1"
  },
    {
    "photo1": "https://encrypted-tbn0.gstatic.com/images?q=tbn:ANd9GcRq8MOMM0TOAQkJGW0_YC7c0ifKGkVYFCF5OHijX-2m3w&s=10",
    "name1": "Luxembourg",
    "photo2": "https://encrypted-tbn0.gstatic.com/images?q=tbn:ANd9GcS-D4qtX_ZMhoH4DnzqkhRz2PxQXTzQ7kMpfTX3gk65zQ&s",
    "name2": "Azerbaidjan",
    "champ": "Basket-ball. Championna d'Europe FIBA",
    "heure": "17H00",
    "date": "02/07/2026",
    "pro": "V1 et TM(156.5) Non"
  },
  {
    "photo1": "https://encrypted-tbn0.gstatic.com/images?q=tbn:ANd9GcT5WSEw7DAphRqS55gwQKgUOWFZ_TgV9ANzZlGKjFhHzA&s=10",
    "name1": "Deportivo San Jose",
    "photo2": "https://encrypted-tbn0.gstatic.com/images?q=tbn:ANd9GcRctbb9aY7F_zlS1Q6sC0JccEYENl35jCAVBnGsq07siA&s=10",
    "name2": "Olimpia Kings",
    "champ": "Basket-ball. Championna du Paraguay",
    "heure": "22H30",
    "date": "02/07/2026",
    "pro": "Handicap: 2(1.5)"
  },
  {
    "photo1": "https://encrypted-tbn0.gstatic.com/images?q=tbn:ANd9GcQvKAtl-HSRiMKLad_odVOYTn4NjlMRZFws721zEDQIug&s=10",
    "name1": "Flamengo U22",
    "photo2": "https://upload.wikimedia.org/wikipedia/en/b/b2/Ca%C3%B1eros-este.png",
    "name2": "Team Klun Academy U22",
    "champ": "Basket-ball. Championna du Brésil. Ligue Carioca U22",
    "heure": "22H30",
    "date": "02/07/2026",
    "pro": "Handicap: 2(54.5)"
  },
  {
    "photo1": "https://encrypted-tbn0.gstatic.com/images?q=tbn:ANd9GcSY-zaO7m7yCBS60D_6JdVDVsso39NtneUls1Gtf9kSJQ&s",
    "name1": "Sao Jose U20",
    "photo2": "https://encrypted-tbn0.gstatic.com/images?q=tbn:ANd9GcRy0gIGb6b3YyqnUHr63oQaLsjbhjwXdVw4elafiN5xqQ&s=10",
    "name2": "Rio Claro U20",
    "champ": "Basket-ball. U20. Equipes nationales",
    "heure": "22H00",
    "date": "02/07/2026",
    "pro": "Total: (+149.5)"
  },
  {
    "photo1": "https://encrypted-tbn0.gstatic.com/images?q=tbn:ANd9GcQ67lFCsm4-uOgguu7smI-i2X4cFKY_mROlgnNQ7oA0Uw&s",
    "name1": "Mystics de Washington (femmes)",
    "photo2": "https://encrypted-tbn0.gstatic.com/images?q=tbn:ANd9GcQ1Z_SHGi9kknRsuY6oljHNQmY4xad1RnBwy75UOT3MBQ&s=10",
    "name2": "Dream d'Atlanta (femmes)",
    "champ": "Basket-ball. WNBA",
    "heure": "23H30",
    "date": "02/07/2026",
    "pro": "Equipe gagne: V2"
  },
   {
    "photo1": "https://encrypted-tbn0.gstatic.com/images?q=tbn:ANd9GcRKEk-3lGkPhIRHzpJV7bwQhtEjoPsMv5MZgiD4KWY5xQ&s=10",
    "name1": "Sun du Connecticut (Femmes)",
    "photo2": "https://encrypted-tbn0.gstatic.com/images?q=tbn:ANd9GcSLjHgc2Z5M5w1fugoViap4KmSKMRmd_7kWU-1ZNj2qRw&s=10",
    "name2": "Wings de Dallas (Femmes)",
    "champ": "Basket-ball. WNBA",
    "heure": "00H00",
    "date": "03/07/2026",
    "pro": "Equipe gagne: V2"
  },
  {
    "photo1": "https://encrypted-tbn0.gstatic.com/images?q=tbn:ANd9GcSu1RwtaPdVUJ4UlXOY_uOUZLZh8AXFasy6lH6AXY1Ftg&s",
    "name1": "Mercurry de Phoenix (Femmes)",
    "photo2": "https://encrypted-tbn0.gstatic.com/images?q=tbn:ANd9GcS3LIipXONY-C6P_6qIwJMW6IPxn8dTiWEfr8JYIVyKlw&s=10",
    "name2": "Storm de Seattle (Femmes)",
    "champ": "Basket-ball. WNBA",
    "heure": "00H00",
    "date": "03/07/2026",
    "pro": "Double chance: 1X"
  }
]
