[
  {
    "photo1": "https://upload.wikimedia.org/wikipedia/en/0/0a/Avtomobilist_Yekaterinburg_Logo.png",
    "name1": "Avtomobilist",
    "photo2": "https://upload.wikimedia.org/wikipedia/commons/thumb/c/c6/HC_SKA_Logo_2023.svg/1200px-HC_SKA_Logo_2023.svg.png",
    "name2": "SKA Saint-Pétersbourg",
    "champ": "Hockey sur glace. Ligue Continentale",
    "heure": "14H00",
    "date": "08/10/2025",
    "pro": "Total: (+4)"
  },
  {
    "photo1": "https://upload.wikimedia.org/wikipedia/fr/thumb/4/49/OHK_Dinamo.png/250px-OHK_Dinamo.png",
    "name1": "Dynamo Moscou",
    "photo2": "https://upload.wikimedia.org/wikipedia/fr/4/40/Salavat_Ioula%C3%AFev_Oufa.png",
    "name2": "Salavat Ioulaïev",
    "champ": "Hockey sur glace. Ligue Continentale",
    "heure": "16H30",
    "date": "08/10/2025",
    "pro": "1X"
  },
    {
    "photo1": "https://upload.wikimedia.org/wikipedia/fr/5/53/Detroit_Tigers_primary_logo_2016.png",
    "name1": "Tigres de Détroit",
    "photo2": "https://upload.wikimedia.org/wikipedia/fr/f/f3/SeattleMariners_100.png",
    "name2": "Mariners de Seattle",
    "champ": "Baseball. États-Unis. MLB",
    "heure": "19H08",
    "date": "08/10/2025",
    "pro": "Total: (+7)"
  },
    {
    "photo1": "https://upload.wikimedia.org/wikipedia/commons/thumb/8/80/Chicago_Cubs_logo.svg/1191px-Chicago_Cubs_logo.svg.png",
    "name1": "Chicago Cubs",
    "photo2": "https://upload.wikimedia.org/wikipedia/fr/a/ab/Brewers_de_Milwaukee_2020.png",
    "name2": "Brewers de Milwaukee",
    "champ": "Baseball. États-Unis. MLB",
    "heure": "21H08",
    "date": "08/10/2025",
    "pro": "Total: (+5)"
  }
]
