[
  {
    "photo1": "https://upload.wikimedia.org/wikipedia/commons/thumb/b/b3/Popyrin_RG19_%2846%29_%2848199101562%29.jpg/280px-Popyrin_RG19_%2846%29_%2848199101562%29.jpg",
    "name1": "Alexei Popyrin",
    "photo2": "https://upload.wikimedia.org/wikipedia/commons/thumb/7/70/Draper_MCM23_%2855%29_%2852883527225%29.jpg/250px-Draper_MCM23_%2855%29_%2852883527225%29.jpg",
    "name2": "Jack  Draper",
    "champ": "ATP Doha",
    "heure": "16H00",
    "date": "17/02/2025",
    "pro": "Handicap 1 (4.5)"
  },
  {
    "photo1": "https://upload.wikimedia.org/wikipedia/commons/6/64/Cerundolo_JM._RGQ22_%283%29_%2852128606242%29.jpg",
    "name1": "Juan Manuel",
    "photo2": "https://upload.wikimedia.org/wikipedia/commons/thumb/5/5f/Jarry_RGQ22_%2818%29_%2852128532452%29.jpg/250px-Jarry_RGQ22_%2818%29_%2852128532452%29.jpg",
    "name2": "Nicolas Jarry",
    "champ": "ATP Doha",
    "heure": "20H30",
    "date": "17/02/2025",
    "pro": "V2"
  },
  {
    "photo1": "https://upload.wikimedia.org/wikipedia/commons/b/bb/Ons_Jabeur_%2851314432345%29.jpg",
    "name1": "Ons Jabeur",
    "photo2": "https://upload.wikimedia.org/wikipedia/commons/c/c4/Peyton_Stearns_US_Open_%28cropped%29.jpg",
    "name2": "Peyton Stearns",
    "champ": "WTA Dubai",
    "heure": "14H30",
    "date": "17/02/2025",
    "pro": "V1"
  }
]
