[
  {
    "photo1": "https://thumbs.dreamstime.com/z/olympiacos-f-c-piraeus-greece-feb-vector-illustration-basketball-logo-87289341.jpg",
    "name1": "Olympiakos Le Piréé",
    "photo2": "https://upload.wikimedia.org/wikipedia/fr/thumb/a/a4/Logo_Fenerbah%C3%A7e_SK_1910.svg/langfr-250px-Logo_Fenerbah%C3%A7e_SK_1910.svg.png",
    "name2": "Fenerbahce",
    "champ": "Basket-ball. Euroligue",
    "heure": "15H00",
    "date": "22/05/2026",
    "pro": "Total: (+151.5)"
  },
  {
    "photo1": "https://encrypted-tbn0.gstatic.com/images?q=tbn:ANd9GcRB1aMgmWEIRD3a92yyJquGcc_h0yjjcTZ9eQ&s",
    "name1": "Valencia",
    "photo2": "https://upload.wikimedia.org/wikipedia/en/b/be/Real_Madrid_Baloncesto.png",
    "name2": "Real Madrid Baloncesto",
    "champ": "Basket-ball. Euroligue",
    "heure": "18H00",
    "date": "22/05/2026",
    "pro": "Handicap: 1(4)"
  },
    {
    "photo1": "https://upload.wikimedia.org/wikipedia/fr/1/1f/Unics_big.gif",
    "name1": "UNICS",
    "photo2": "https://upload.wikimedia.org/wikipedia/fr/thumb/4/45/Logo_Z%C3%A9nith_Saint-P%C3%A9tersbourg_2023.svg/langfr-250px-Logo_Z%C3%A9nith_Saint-P%C3%A9tersbourg_2023.svg.png",
    "name2": "Zénith Saint-Pétersbourg",
    "champ": "Basket-ball. VTB United Ligue",
    "heure": "16H30",
    "date": "22/05/2026",
    "pro": "Total: (+158.5)"
  },
  {
    "photo1": "https://upload.wikimedia.org/wikipedia/en/d/d5/SC_Rasta_Vechta_logo.jpg",
    "name1": "SC Rasta Vechta",
    "photo2": "https://upload.wikimedia.org/wikipedia/fr/thumb/f/fa/Alba_Berlin_%28logo%29.svg/1280px-Alba_Berlin_%28logo%29.svg.png",
    "name2": "ALBA Berlin",
    "champ": "Basket-ball. Championnat d'Allemagne",
    "heure": "16H30",
    "date": "22/05/2026",
    "pro": "Handicap: 2(5.5)"
  },
  {
    "photo1": "https://upload.wikimedia.org/wikipedia/commons/7/78/WUE_Primary_Logo_rot_transparent_CMYK.png",
    "name1": "Wurzburg",
    "photo2": "https://upload.wikimedia.org/wikipedia/en/thumb/c/cd/Telekom_Baskets_Bonn_logo.svg/1280px-Telekom_Baskets_Bonn_logo.svg.png",
    "name2": "Telekom Baskets Bonn",
    "champ": "Basket-ball. Championnat d'Allemagne",
    "heure": "18H30",
    "date": "22/05/2026",
    "pro": "1X"
  },
  {
    "photo1": "https://encrypted-tbn0.gstatic.com/images?q=tbn:ANd9GcQRPLmx0fWcBRbmMAEL9UTUBM1ajo-ASqKswg&s",
    "name1": "Borisfen Mogilev",
    "photo2": "https://upload.wikimedia.org/wikipedia/ru/3/3f/BC_Rubon.jpg",
    "name2": "Rubon",
    "champ": "Basket-ball. Championnat de Biélorussie",
    "heure": "15H30",
    "date": "22/05/2026",
    "pro": "Equipe gagne: V1"
  },
  {
    "photo1": "https://upload.wikimedia.org/wikipedia/fr/c/c2/Logo_STB_Le_Havre_-_2022.svg?utm_source=fr.wikipedia.org&utm_campaign=index&utm_content=original",
    "name1": "Le Havre",
    "photo2": "https://encrypted-tbn0.gstatic.com/images?q=tbn:ANd9GcRMEofe7OP13d7_71VroYx0AZ2q5hBdH3sc3w&s",
    "name2": "CEP Lorient",
    "champ": "Basket-ball. Championnat de France",
    "heure": "18H00",
    "date": "22/05/2026",
    "pro": "Total: (+156.5)"
  },
   {
    "photo1": "https://upload.wikimedia.org/wikipedia/fr/thumb/0/0b/Logo_Mulhouse_Mustangs_-_2025.svg/1280px-Logo_Mulhouse_Mustangs_-_2025.svg.png",
    "name1": "Mulhouse Basket",
    "photo2": "https://encrypted-tbn0.gstatic.com/images?q=tbn:ANd9GcRlotiFL6BEGs_oTk7V-Cm88IDgq-YFziqOpA&s",
    "name2": "Tours Metropole",
    "champ": "Basket-ball. Championnat de France",
    "heure": "18H00",
    "date": "22/05/2026",
    "pro": "Equipe gagne: V1"
  },
  {
    "photo1": "https://upload.wikimedia.org/wikipedia/fr/thumb/7/7e/Logo_Fos_Provence_Basket_-_2019.svg/1280px-Logo_Fos_Provence_Basket_-_2019.svg.png",
    "name1": "Fos Ouest Provence",
    "photo2": "https://upload.wikimedia.org/wikipedia/commons/thumb/8/8d/Logo_Basket_Club_Orchies_-_2025.svg/1280px-Logo_Basket_Club_Orchies_-_2025.svg.png",
    "name2": "Orchies",
    "champ": "Basket-ball. Championnat de France",
    "heure": "18H00",
    "date": "22/05/2026",
    "pro": "Total: (+154.5)"
  },
  {
    "photo1": "https://upload.wikimedia.org/wikipedia/fr/thumb/9/9e/Thunder_d%27Oklahoma_City.svg/1280px-Thunder_d%27Oklahoma_City.svg.png",
    "name1": "San Antonio Spurs",
    "photo2": "https://upload.wikimedia.org/wikipedia/fr/6/6f/Cavs_de_Cleveland_logo_2003.png",
    "name2": "Oklahoma City Thunder",
    "champ": "Basket-ball. NBA",
    "heure": "00H30",
    "date": "23/05/2026",
    "pro": "Total: (+209.5)"
  }
]
